onelogin_aws_cli/__init__.py
onelogin_aws_cli/argparse.py
onelogin_aws_cli/cli.py
onelogin_aws_cli/configuration.py
onelogin_aws_cli/credentials.py
onelogin_aws_cli/userquery.py
onelogin_aws_cli-0.1.19.dist-info/LICENSE.txt
onelogin_aws_cli-0.1.19.dist-info/METADATA
onelogin_aws_cli-0.1.19.dist-info/WHEEL
onelogin_aws_cli-0.1.19.dist-info/entry_points.txt
onelogin_aws_cli-0.1.19.dist-info/top_level.txt
onelogin_aws_cli-0.1.19.dist-info/RECORD
