Metadata-Version: 2.1
Name: onelogin-aws-cli
Version: 0.1.19
Summary: Onelogin assume AWS role through CLI
Home-page: https://github.com/physera/onelogin-aws-cli
Download-URL: https://github.com/physera/onelogin-aws-cli/archive/0.1.19.tar.gz
Author: Cameron Marlow
Author-email: cameron@physera.com
License: MIT License
Keywords: onelogin aws cli
Classifier: Development Status :: 4 - Beta
Classifier: Environment :: Console
Classifier: License :: OSI Approved :: MIT License
Classifier: Programming Language :: Python :: 3.5
Classifier: Programming Language :: Python :: 3.6
Classifier: Programming Language :: Python :: 3 :: Only
Classifier: Topic :: Security
Classifier: Topic :: System :: Systems Administration :: Authentication/Directory
Requires-Python: >=3
License-File: LICENSE.txt
Requires-Dist: boto3
Requires-Dist: onelogin (<3.0,>=2.0)
Requires-Dist: keyring
Requires-Dist: requests
